{
    "data": [
      {
        "ids": "DS748294",
        "designation": "Technical Head",
        "status": "Active"
      },
      {
        "ids": "DS748293",
        "designation": "Accountant",
        "status": "Active"
      },
      {
        "ids": "DS748292",
        "designation": "Teacher",
        "status": "Active"
      },
      {
        "ids": "DS748291",
        "designation": "Librarian",
        "status": "Active"
      },
      {
        "ids": "DS748290",
        "designation": "Doctor",
        "status": "Inactive"
      },
      {
        "ids": "DS748289",
        "designation": "Driver",
        "status": "Active"
      },
      {
        "ids": "DS748288",
        "designation": "Warden",
        "status": "Active"
      },
      {
        "ids": "DS748287",
        "designation": "Receptionist",
        "status": "Active"
      },
      {
        "ids": "DS748286",
        "designation": "Therapist",
        "status": "Inactive"
      },
      {
        "ids": "DS748285",
        "designation": "Coach",
        "status": "Active"
      }
    ],
    "totalData": 10
  }
  