{
    "data": [
        {
            
            "id": "H823828",
            "hostelName": "Phoenix Resence",
            "hostelType": "Boys",
            "address": "25 Crowfield Road, Phoenix",
            "inTake": "150",
            "description": "Rising to nurture young minds"
          },
          {
            
            "id": "H823827",
            "hostelName": "Tranquil Haven",
            "hostelType": "Girls",
            "address": "81 Hartland Avenue, Milwaukee",
            "inTake": "200",
            "description": "Rising to nurture young minds"
          },
          {
            
            "id": "H823826",
            "hostelName": "Radiant Towers",
            "hostelType": "Boys",
            "address": "School Campus",
            "inTake": "180",
            "description": "Illuminating minds with knowledge and warmth"
          },
          {
            
            "id": "H823825",
            "hostelName": "Nova Nest",
            "hostelType": "Girls",
            "address": "School Campus",
            "inTake": "180",
            "description": "A nestling ground for budding intellectuals to thrive"
          },
          {
            
            "id": "H823824",
            "hostelName": "Vista Villat",
            "hostelType": "Boys",
            "address": "65 Braxton Street, Sheffield",
            "inTake": "250",
            "description": "Overlooking the vast landscape of knowledge"
          },
          {
            
            "id": "H823823",
            "hostelName": "Zenith Zone",
            "hostelType": "Girls",
            "address": "School Campus",
            "inTake": "150",
            "description": "Living at the peak of academic achievement"
          },
          {
            
            "id": "H823822",
            "hostelName": "Summit Springs",
            "hostelType": "Boys",
            "address": "55 Upton Avenue, Monson",
            "inTake": "300",
            "description": "Drawing from the wellspring of knowledge"
          },
          {
            
            "id": "H823821",
            "hostelName": "Beacon Breeze",
            "hostelType": "Girls",
            "address": "School Campus",
            "inTake": "280",
            "description": "Ring the winds of educational inspiration"
          },
          {
            
            "id": "H823820",
            "hostelName": "Empyrean Estate",
            "hostelType": "Boys",
            "address": "45 Cinnamon Lane, San Antonio",
            "inTake": "200",
            "description": "Infusing energy into scholarly endeavors"
          },
          {
            
            "id": "H823819",
            "hostelName": "Nexus Nook",
            "hostelType": "Girls",
            "address": "School Campus",
            "inTake": "350",
            "description": "A communal hub for academic excellence"
          }
    ],
    "totalData": 10
  }
  